{
  "table_name": "marketing_email_details",
  "description": "HubSpot marketing email detail — GET /marketing/v3/emails/{emailId}",
  "source_path": null,
  "has_pagination": false,
  "context_fields": ["email_id"],
  "fields": [
    {"column": "id",                               "source": "id",                                       "type": "string"},
    {"column": "name",                             "source": "name",                                     "type": "string"},
    {"column": "subject",                          "source": "subject",                                  "type": "string"},
    {"column": "state",                            "source": "state",                                    "type": "string"},
    {"column": "type",                             "source": "type",                                     "type": "string"},
    {"column": "subcategory",                      "source": "subcategory",                              "type": "string"},
    {"column": "language",                         "source": "language",                                 "type": "string"},
    {"column": "archived",                         "source": "archived",                                 "type": "boolean"},
    {"column": "is_ab",                            "source": "isAb",                                     "type": "boolean"},
    {"column": "is_published",                     "source": "isPublished",                              "type": "boolean"},
    {"column": "is_transactional",                 "source": "isTransactional",                          "type": "boolean"},
    {"column": "send_on_publish",                  "source": "sendOnPublish",                            "type": "boolean"},
    {"column": "jitter_send_time",                 "source": "jitterSendTime",                           "type": "boolean"},
    {"column": "active_domain",                    "source": "activeDomain",                             "type": "string"},
    {"column": "campaign",                         "source": "campaign",                                 "type": "string"},
    {"column": "campaign_name",                    "source": "campaignName",                             "type": "string"},
    {"column": "campaign_utm",                     "source": "campaignUtm",                              "type": "string"},
    {"column": "email_campaign_group_id",          "source": "emailCampaignGroupId",                     "type": "string"},
    {"column": "primary_email_campaign_id",        "source": "primaryEmailCampaignId",                   "type": "string"},
    {"column": "email_template_mode",              "source": "emailTemplateMode",                        "type": "string"},
    {"column": "feedback_survey_id",               "source": "feedbackSurveyId",                         "type": "string"},
    {"column": "folder_id",                        "source": "folderId",                                 "type": "string"},
    {"column": "business_unit_id",                 "source": "businessUnitId",                           "type": "string"},
    {"column": "cloned_from",                      "source": "clonedFrom",                               "type": "string"},
    {"column": "preview_key",                      "source": "previewKey",                               "type": "string"},
    {"column": "publish_date",                     "source": "publishDate",                              "type": "string"},
    {"column": "published_at",                     "source": "publishedAt",                              "type": "string"},
    {"column": "unpublished_at",                   "source": "unpublishedAt",                            "type": "string"},
    {"column": "published_by_email",               "source": "publishedByEmail",                         "type": "string"},
    {"column": "published_by_id",                  "source": "publishedById",                            "type": "string"},
    {"column": "published_by_name",                "source": "publishedByName",                          "type": "string"},
    {"column": "created_at",                       "source": "createdAt",                                "type": "string"},
    {"column": "created_by_id",                    "source": "createdById",                              "type": "string"},
    {"column": "deleted_at",                       "source": "deletedAt",                                "type": "string"},
    {"column": "updated_at",                       "source": "updatedAt",                                "type": "string"},
    {"column": "updated_by_id",                    "source": "updatedById",                              "type": "string"},
    {"column": "from_name",                        "source": "from.fromName",                            "type": "string"},
    {"column": "from_reply_to",                    "source": "from.replyTo",                             "type": "string"},
    {"column": "from_custom_reply_to",             "source": "from.customReplyTo",                       "type": "string"},
    {"column": "subscription_id",                  "source": "subscriptionDetails.subscriptionId",       "type": "string"},
    {"column": "subscription_name",                "source": "subscriptionDetails.subscriptionName",     "type": "string"},
    {"column": "subscription_office_location_id",  "source": "subscriptionDetails.officeLocationId",     "type": "string"},
    {"column": "subscription_preferences_group_id","source": "subscriptionDetails.preferencesGroupId",   "type": "string"},
    {"column": "webversion_url",                   "source": "webversion.url",                           "type": "string"},
    {"column": "webversion_enabled",               "source": "webversion.enabled",                       "type": "boolean"},
    {"column": "content_json",                     "source": "content",                                  "type": "json"},
    {"column": "stats_json",                       "source": "stats",                                    "type": "json"},
    {"column": "testing_json",                     "source": "testing",                                  "type": "json"},
    {"column": "rss_data_json",                    "source": "rssData",                                  "type": "json"},
    {"column": "to_json",                          "source": "to",                                       "type": "json"},
    {"column": "all_email_campaign_ids_json",      "source": "allEmailCampaignIds",                      "type": "json"},
    {"column": "teams_with_access_json",           "source": "teamsWithAccess",                          "type": "json"},
    {"column": "workflow_names_json",              "source": "workflowNames",                            "type": "json"}
  ]
}
